pyangles/__init__.py
pyangles/main.py
pyangles-0.0.22.dist-info/LICENSE
pyangles-0.0.22.dist-info/METADATA
pyangles-0.0.22.dist-info/WHEEL
pyangles-0.0.22.dist-info/top_level.txt
pyangles-0.0.22.dist-info/RECORD
