Metadata-Version: 2.1
Name: pyangles
Version: 0.0.22
Summary: identify chart patterns in series dataframe
Home-page: http://github.com/pbringetto/pyangles
Author: Paul Bringetto
Author-email: plbriqto@gmail.com
Project-URL: Bug Tracker, http://github.com/pbringetto/pyangles/issues
Classifier: Programming Language :: Python :: 3
Classifier: License :: OSI Approved :: MIT License
Classifier: Operating System :: OS Independent
Requires-Python: >=3.6
License-File: LICENSE
Requires-Dist: pandas
Requires-Dist: numpy
Requires-Dist: scipy
Requires-Dist: python-math
